ChromeKaifagongjuZhinan/README.md
ChromeKaifagongjuZhinan/__init__.py
ChromeKaifagongjuZhinan/__main__.py
ChromeKaifagongjuZhinan/file.epub
ChromeKaifagongjuZhinan/index.html
ChromeKaifagongjuZhinan/css/__init__.py
ChromeKaifagongjuZhinan/css/annotations.css
ChromeKaifagongjuZhinan/css/main.css
ChromeKaifagongjuZhinan/css/normalize.css
ChromeKaifagongjuZhinan/css/popup.css
ChromeKaifagongjuZhinan/font/__init__.py
ChromeKaifagongjuZhinan/font/fontello.eot
ChromeKaifagongjuZhinan/font/fontello.svg
ChromeKaifagongjuZhinan/font/fontello.ttf
ChromeKaifagongjuZhinan/font/fontello.woff
ChromeKaifagongjuZhinan/img/__init__.py
ChromeKaifagongjuZhinan/img/annotator-glyph-sprite.png
ChromeKaifagongjuZhinan/img/annotator-icon-sprite.png
ChromeKaifagongjuZhinan/img/apple-touch-icon.png
ChromeKaifagongjuZhinan/img/cancelfullscreen.png
ChromeKaifagongjuZhinan/img/close.png
ChromeKaifagongjuZhinan/img/fullscreen.png
ChromeKaifagongjuZhinan/img/loader.gif
ChromeKaifagongjuZhinan/img/menu-icon.png
ChromeKaifagongjuZhinan/img/save.png
ChromeKaifagongjuZhinan/img/saved.png
ChromeKaifagongjuZhinan/img/settings-s.png
ChromeKaifagongjuZhinan/img/settings.png
ChromeKaifagongjuZhinan/img/star.png
ChromeKaifagongjuZhinan/js/__init__.py
ChromeKaifagongjuZhinan/js/epub.js
ChromeKaifagongjuZhinan/js/epub.min.js
ChromeKaifagongjuZhinan/js/epub.min.map
ChromeKaifagongjuZhinan/js/hooks.min.js
ChromeKaifagongjuZhinan/js/hooks.min.map
ChromeKaifagongjuZhinan/js/reader.js
ChromeKaifagongjuZhinan/js/reader.js.map
ChromeKaifagongjuZhinan/js/reader.min.js
ChromeKaifagongjuZhinan/js/reader.min.map
ChromeKaifagongjuZhinan/js/hooks/__init__.py
ChromeKaifagongjuZhinan/js/hooks/extensions/__init__.py
ChromeKaifagongjuZhinan/js/hooks/extensions/highlight.js
ChromeKaifagongjuZhinan/js/libs/__init__.py
ChromeKaifagongjuZhinan/js/libs/jquery.min.js
ChromeKaifagongjuZhinan/js/libs/localforage.min.js
ChromeKaifagongjuZhinan/js/libs/screenfull.js
ChromeKaifagongjuZhinan/js/libs/screenfull.min.js
chrome_kaifagongju_zhinan-2024.3.2.0.dist-info/METADATA
chrome_kaifagongju_zhinan-2024.3.2.0.dist-info/WHEEL
chrome_kaifagongju_zhinan-2024.3.2.0.dist-info/entry_points.txt
chrome_kaifagongju_zhinan-2024.3.2.0.dist-info/top_level.txt
chrome_kaifagongju_zhinan-2024.3.2.0.dist-info/RECORD
